fnsignal/__init__.py
fnsignal/fnsignal.py
fnsignal-2.5.5.dist-info/METADATA
fnsignal-2.5.5.dist-info/WHEEL
fnsignal-2.5.5.dist-info/licenses/LICENSE
fnsignal-2.5.5.dist-info/RECORD
