Metadata-Version: 2.4
Name: fnsignal
Version: 2.5.5
Summary: A powerful function signal system for Python
Project-URL: Homepage, https://github.com/yourusername/fnsignal
Project-URL: Bug Tracker, https://github.com/yourusername/fnsignal/issues
Author-email: howShouldIChosseMyUsername <trademark2179@gmail.com>
License: MIT
License-File: LICENSE
Requires-Python: >=3.7
Requires-Dist: asyncio>=3.4.3
Requires-Dist: typing-extensions>=4.0.0
